{"upload_date": "20181216", "vcodec": "avc1.640028", "extractor": "youtube", "series": null, "chapters": null, "height": 1080, "like_count": 6, "duration": 56, "fulltitle": "\u751f\u6d3b | \u7f8e\u5973\u6f14\u7ece\u51e0\u4e4e\u7edd\u8ff9\u7684\u201c\u706b\u6f06\u5c01\u7f04\u201d 2018-12-16", "id": "31vbrmNRstk", "album": null, "view_count": 963, "playlist": "Uploads from Weiping Show\u300a\u5e73\u8bba\u300b", "start_time": null, "title": "\u751f\u6d3b | \u7f8e\u5973\u6f14\u7ece\u51e0\u4e4e\u7edd\u8ff9\u7684\u201c\u706b\u6f06\u5c01\u7f04\u201d 2018-12-16", "_filename": "20181216_31vbrmNRstk.mp4", "creator": null, "is_live": null, "playlist_index": 133, "dislike_count": 8, "playlist_id": "UU2VwgzDzUNvfRDqQ6LJxTXA", "abr": 128, "tags": ["\u706b\u6f06\u5c01\u7f04 \u5c01\u8721"], "uploader_url": "http://www.youtube.com/channel/UC2VwgzDzUNvfRDqQ6LJxTXA", "subtitles": {}, "fps": 30, "stretched_ratio": null, "season_number": null, "annotations": null, "webpage_url_basename": "31vbrmNRstk", "acodec": "mp4a.40.2", "display_id": "31vbrmNRstk", "automatic_captions": {}, "description": "\u5723\u8bde\u548c\u5143\u65e6\u5feb\u8981\u5230\u4e86\uff0c\u4f60\u4f1a\u7ed9\u670b\u53cb\u5bc4\u9001\u624b\u5199\u8d3a\u5361\u5417\uff1f\u6709\u5c1d\u8bd5\u8fc7\u53e4\u8001\u7684\u201c\u706b\u6f06\u5c01\u7f04\u201d\u5417\uff1f\u6b22\u8fce\u4e86\u89e3\u3002", "format": "137 - 1920x1080 (1080p)+140 - audio only (DASH audio)", "track": null, "playlist_uploader": "Weiping Show\u300a\u5e73\u8bba\u300b", "average_rating": 2.7142856, "uploader": "Weiping Show\u300a\u5e73\u8bba\u300b", "format_id": "137+140", "episode_number": null, "uploader_id": "UC2VwgzDzUNvfRDqQ6LJxTXA", "categories": ["News & Politics"], "playlist_title": "Uploads from Weiping Show\u300a\u5e73\u8bba\u300b", "thumbnails": [{"url": "https://i.ytimg.com/vi/31vbrmNRstk/maxresdefault.jpg", "id": "0"}], "license": null, "artist": null, "extractor_key": "Youtube", "release_date": null, "alt_title": null, "channel_id": "UC2VwgzDzUNvfRDqQ6LJxTXA", "thumbnail": "https://i.ytimg.com/vi/31vbrmNRstk/maxresdefault.jpg", "vbr": null, "ext": "mp4", "release_year": null, "end_time": null, "webpage_url": "https://www.youtube.com/watch?v=31vbrmNRstk", "formats": [{"http_headers": {"Accept-Charset": "ISO-8859-1,utf-8;q=0.7,*;q=0.7", "Accept-Language": "en-us,en;q=0.5", "Accept-Encoding": "gzip, deflate", "Accept": "text/html,application/xhtml+xml,application/xml;q=0.9,*/*;q=0.8", "User-Agent": "Mozilla/5.0 (Windows NT 10.0; Win64; x64) AppleWebKit/537.36 (KHTML, like Gecko) Chrome/70.0.3538.31 Safari/537.36"}, "format_note": "DASH audio", "protocol": "https", "format": "249 - audio only (DASH audio)", "url": "https://r6---sn-25ge7nse.googlevideo.com/videoplayback?expire=1565854066&ei=ErVUXYPmBZSVkwaTzaDQDA&ip=148.163.76.139&id=o-AB-qyN0zj7U5atdxIcQvWYFcheiuJcStQgtAOw7NIjp7&itag=249&source=youtube&requiressl=yes&mm=31%2C29&mn=sn-25ge7nse%2Csn-25glen7e&ms=au%2Crdu&mv=u&mvi=5&pl=22&mime=audio%2Fwebm&gir=yes&clen=344869&dur=56.201&lmt=1544995220161827&mt=1565831977&fvip=6&keepalive=yes&c=WEB&txp=2301222&sparams=expire%2Cei%2Cip%2Cid%2Citag%2Csource%2Crequiressl%2Cmime%2Cgir%2Cclen%2Cdur%2Clmt&sig=ALgxI2wwRAIgH60-1nP6iheplgFflTNuNxj8Chggai506vLxZoNXmLMCIEYVkB3pm8yTZ4kpcPvOcf_q32rG2eAobt1ggM_Bk_Eb&lsparams=mm%2Cmn%2Cms%2Cmv%2Cmvi%2Cpl&lsig=AHylml4wRQIhAJKMRBbZFB74CYBAKnuiLqB4J6TCs99X5LO2Qy7zt2UoAiBk3TbLfTK2t4HxVEBZe61QM2E7FwhJG9_1EYkDIzc3Tw%3D%3D&ratebypass=yes", "vcodec": "none", "tbr": 51.461, "abr": 50, "player_url": "/yts/jsbin/player_ias-vflLAbfAI/en_US/base.js", "downloader_options": {"http_chunk_size": 10485760}, "ext": "webm", "filesize": 344869, "format_id": "249", "quality": -1, "acodec": "opus"}, {"http_headers": {"Accept-Charset": "ISO-8859-1,utf-8;q=0.7,*;q=0.7", "Accept-Language": "en-us,en;q=0.5", "Accept-Encoding": "gzip, deflate", "Accept": "text/html,application/xhtml+xml,application/xml;q=0.9,*/*;q=0.8", "User-Agent": "Mozilla/5.0 (Windows NT 10.0; Win64; x64) AppleWebKit/537.36 (KHTML, like Gecko) Chrome/70.0.3538.31 Safari/537.36"}, "format_note": "DASH audio", "protocol": "https", "format": "250 - audio only (DASH audio)", "url": "https://r6---sn-25ge7nse.googlevideo.com/videoplayback?expire=1565854066&ei=ErVUXYPmBZSVkwaTzaDQDA&ip=148.163.76.139&id=o-AB-qyN0zj7U5atdxIcQvWYFcheiuJcStQgtAOw7NIjp7&itag=250&source=youtube&requiressl=yes&mm=31%2C29&mn=sn-25ge7nse%2Csn-25glen7e&ms=au%2Crdu&mv=u&mvi=5&pl=22&mime=audio%2Fwebm&gir=yes&clen=451342&dur=56.201&lmt=1544995220292313&mt=1565831977&fvip=6&keepalive=yes&c=WEB&txp=2301222&sparams=expire%2Cei%2Cip%2Cid%2Citag%2Csource%2Crequiressl%2Cmime%2Cgir%2Cclen%2Cdur%2Clmt&sig=ALgxI2wwRQIhAL3orSGEHYs1lFE63t6qHU5ggspuasES3R5C8ASudMATAiBV3xe4-M7jkkt_Q6Q8p0dBRz8MSpzbZgK5GiE-ZVY3zQ%3D%3D&lsparams=mm%2Cmn%2Cms%2Cmv%2Cmvi%2Cpl&lsig=AHylml4wRQIhAJKMRBbZFB74CYBAKnuiLqB4J6TCs99X5LO2Qy7zt2UoAiBk3TbLfTK2t4HxVEBZe61QM2E7FwhJG9_1EYkDIzc3Tw%3D%3D&ratebypass=yes", "vcodec": "none", "tbr": 66.632, "abr": 70, "player_url": "/yts/jsbin/player_ias-vflLAbfAI/en_US/base.js", "downloader_options": {"http_chunk_size": 10485760}, "ext": "webm", "filesize": 451342, "format_id": "250", "quality": -1, "acodec": "opus"}, {"http_headers": {"Accept-Charset": "ISO-8859-1,utf-8;q=0.7,*;q=0.7", "Accept-Language": "en-us,en;q=0.5", "Accept-Encoding": "gzip, deflate", "Accept": "text/html,application/xhtml+xml,application/xml;q=0.9,*/*;q=0.8", "User-Agent": "Mozilla/5.0 (Windows NT 10.0; Win64; x64) AppleWebKit/537.36 (KHTML, like Gecko) Chrome/70.0.3538.31 Safari/537.36"}, "format_note": "DASH audio", "protocol": "https", "format": "251 - audio only (DASH audio)", "url": "https://r6---sn-25ge7nse.googlevideo.com/videoplayback?expire=1565854066&ei=ErVUXYPmBZSVkwaTzaDQDA&ip=148.163.76.139&id=o-AB-qyN0zj7U5atdxIcQvWYFcheiuJcStQgtAOw7NIjp7&itag=251&source=youtube&requiressl=yes&mm=31%2C29&mn=sn-25ge7nse%2Csn-25glen7e&ms=au%2Crdu&mv=u&mvi=5&pl=22&mime=audio%2Fwebm&gir=yes&clen=892054&dur=56.201&lmt=1544995221881157&mt=1565831977&fvip=6&keepalive=yes&c=WEB&txp=2301222&sparams=expire%2Cei%2Cip%2Cid%2Citag%2Csource%2Crequiressl%2Cmime%2Cgir%2Cclen%2Cdur%2Clmt&sig=ALgxI2wwRgIhAJuiOUhfH6VU2gO6vFef4SJ67aPi-oO40_VkibLrTUmeAiEAjkAzQL0V_KK2BLGBS_lxM-MZSSyQnHhr2OaClBMBdeY%3D&lsparams=mm%2Cmn%2Cms%2Cmv%2Cmvi%2Cpl&lsig=AHylml4wRQIhAJKMRBbZFB74CYBAKnuiLqB4J6TCs99X5LO2Qy7zt2UoAiBk3TbLfTK2t4HxVEBZe61QM2E7FwhJG9_1EYkDIzc3Tw%3D%3D&ratebypass=yes", "vcodec": "none", "tbr": 129.506, "abr": 160, "player_url": "/yts/jsbin/player_ias-vflLAbfAI/en_US/base.js", "downloader_options": {"http_chunk_size": 10485760}, "ext": "webm", "filesize": 892054, "format_id": "251", "quality": -1, "acodec": "opus"}, {"http_headers": {"Accept-Charset": "ISO-8859-1,utf-8;q=0.7,*;q=0.7", "Accept-Language": "en-us,en;q=0.5", "Accept-Encoding": "gzip, deflate", "Accept": "text/html,application/xhtml+xml,application/xml;q=0.9,*/*;q=0.8", "User-Agent": "Mozilla/5.0 (Windows NT 10.0; Win64; x64) AppleWebKit/537.36 (KHTML, like Gecko) Chrome/70.0.3538.31 Safari/537.36"}, "tbr": 130.486, "container": "m4a_dash", "format": "140 - audio only (DASH audio)", "url": "https://r6---sn-25ge7nse.googlevideo.com/videoplayback?expire=1565854066&ei=ErVUXYPmBZSVkwaTzaDQDA&ip=148.163.76.139&id=o-AB-qyN0zj7U5atdxIcQvWYFcheiuJcStQgtAOw7NIjp7&itag=140&source=youtube&requiressl=yes&mm=31%2C29&mn=sn-25ge7nse%2Csn-25glen7e&ms=au%2Crdu&mv=u&mvi=5&pl=22&mime=audio%2Fmp4&gir=yes&clen=910986&dur=56.238&lmt=1544988176403673&mt=1565831977&fvip=6&keepalive=yes&c=WEB&txp=2311222&sparams=expire%2Cei%2Cip%2Cid%2Citag%2Csource%2Crequiressl%2Cmime%2Cgir%2Cclen%2Cdur%2Clmt&sig=ALgxI2wwRAIgBSwSK1iGo6dIMEozscR1w07f7wFsXD1KagZhNIeaF5cCIFGoKhd-BNABMyv1lmjO7Rpr4uiPdIcmwzXI_jJMhpno&lsparams=mm%2Cmn%2Cms%2Cmv%2Cmvi%2Cpl&lsig=AHylml4wRQIhAJKMRBbZFB74CYBAKnuiLqB4J6TCs99X5LO2Qy7zt2UoAiBk3TbLfTK2t4HxVEBZe61QM2E7FwhJG9_1EYkDIzc3Tw%3D%3D&ratebypass=yes", "vcodec": "none", "format_note": "DASH audio", "abr": 128, "player_url": "/yts/jsbin/player_ias-vflLAbfAI/en_US/base.js", "downloader_options": {"http_chunk_size": 10485760}, "ext": "m4a", "filesize": 910986, "protocol": "https", "format_id": "140", "quality": -1, "acodec": "mp4a.40.2"}, {"http_headers": {"Accept-Charset": "ISO-8859-1,utf-8;q=0.7,*;q=0.7", "Accept-Language": "en-us,en;q=0.5", "Accept-Encoding": "gzip, deflate", "Accept": "text/html,application/xhtml+xml,application/xml;q=0.9,*/*;q=0.8", "User-Agent": "Mozilla/5.0 (Windows NT 10.0; Win64; x64) AppleWebKit/537.36 (KHTML, like Gecko) Chrome/70.0.3538.31 Safari/537.36"}, "tbr": 97.311, "container": "webm", "format": "278 - 256x144 (144p)", "url": "https://r6---sn-25ge7nse.googlevideo.com/videoplayback?expire=1565854066&ei=ErVUXYPmBZSVkwaTzaDQDA&ip=148.163.76.139&id=o-AB-qyN0zj7U5atdxIcQvWYFcheiuJcStQgtAOw7NIjp7&itag=278&aitags=133%2C134%2C135%2C136%2C137%2C160%2C242%2C243%2C244%2C247%2C248%2C278&source=youtube&requiressl=yes&mm=31%2C29&mn=sn-25ge7nse%2Csn-25glen7e&ms=au%2Crdu&mv=u&mvi=5&pl=22&mime=video%2Fwebm&gir=yes&clen=670333&dur=56.156&lmt=1544997310923233&mt=1565831977&fvip=6&keepalive=yes&c=WEB&txp=2301222&sparams=expire%2Cei%2Cip%2Cid%2Caitags%2Csource%2Crequiressl%2Cmime%2Cgir%2Cclen%2Cdur%2Clmt&sig=ALgxI2wwRQIhALVtFxoBL-Y5hoxJ3_lVjibX_WZLCuHRX7qzEg8_rLXJAiA9gD_c-QJYzcxiADAiNjgsCw6gxtT8G9NrFXnlZIjmfw%3D%3D&lsparams=mm%2Cmn%2Cms%2Cmv%2Cmvi%2Cpl&lsig=AHylml4wRQIhAJKMRBbZFB74CYBAKnuiLqB4J6TCs99X5LO2Qy7zt2UoAiBk3TbLfTK2t4HxVEBZe61QM2E7FwhJG9_1EYkDIzc3Tw%3D%3D&ratebypass=yes", "vcodec": "vp9", "format_note": "144p", "player_url": "/yts/jsbin/player_ias-vflLAbfAI/en_US/base.js", "downloader_options": {"http_chunk_size": 10485760}, "width": 256, "ext": "webm", "filesize": 670333, "fps": 30, "protocol": "https", "format_id": "278", "height": 144, "quality": -1, "acodec": "none"}, {"format_note": "144p", "protocol": "https", "format": "160 - 256x144 (144p)", "tbr": 123.738, "height": 144, "downloader_options": {"http_chunk_size": 10485760}, "format_id": "160", "quality": -1, "http_headers": {"Accept-Charset": "ISO-8859-1,utf-8;q=0.7,*;q=0.7", "Accept-Language": "en-us,en;q=0.5", "Accept-Encoding": "gzip, deflate", "Accept": "text/html,application/xhtml+xml,application/xml;q=0.9,*/*;q=0.8", "User-Agent": "Mozilla/5.0 (Windows NT 10.0; Win64; x64) AppleWebKit/537.36 (KHTML, like Gecko) Chrome/70.0.3538.31 Safari/537.36"}, "url": "https://r6---sn-25ge7nse.googlevideo.com/videoplayback?expire=1565854066&ei=ErVUXYPmBZSVkwaTzaDQDA&ip=148.163.76.139&id=o-AB-qyN0zj7U5atdxIcQvWYFcheiuJcStQgtAOw7NIjp7&itag=160&aitags=133%2C134%2C135%2C136%2C137%2C160%2C242%2C243%2C244%2C247%2C248%2C278&source=youtube&requiressl=yes&mm=31%2C29&mn=sn-25ge7nse%2Csn-25glen7e&ms=au%2Crdu&mv=u&mvi=5&pl=22&mime=video%2Fmp4&gir=yes&clen=658693&dur=56.156&lmt=1544988176772478&mt=1565831977&fvip=6&keepalive=yes&c=WEB&txp=2311222&sparams=expire%2Cei%2Cip%2Cid%2Caitags%2Csource%2Crequiressl%2Cmime%2Cgir%2Cclen%2Cdur%2Clmt&sig=ALgxI2wwRAIgAihO_xmYWjgJnjbZapGD80Xm1FgmWG6gxJ97AZJosBQCIFt-tDntpjUNJqRJTYHfMtS1pRNMzqnE27j3cJNV_NIB&lsparams=mm%2Cmn%2Cms%2Cmv%2Cmvi%2Cpl&lsig=AHylml4wRQIhAJKMRBbZFB74CYBAKnuiLqB4J6TCs99X5LO2Qy7zt2UoAiBk3TbLfTK2t4HxVEBZe61QM2E7FwhJG9_1EYkDIzc3Tw%3D%3D&ratebypass=yes", "vcodec": "avc1.4d400c", "player_url": "/yts/jsbin/player_ias-vflLAbfAI/en_US/base.js", "width": 256, "ext": "mp4", "filesize": 658693, "fps": 30, "acodec": "none"}, {"format_note": "240p", "protocol": "https", "format": "242 - 426x240 (240p)", "tbr": 221.503, "height": 240, "downloader_options": {"http_chunk_size": 10485760}, "format_id": "242", "quality": -1, "http_headers": {"Accept-Charset": "ISO-8859-1,utf-8;q=0.7,*;q=0.7", "Accept-Language": "en-us,en;q=0.5", "Accept-Encoding": "gzip, deflate", "Accept": "text/html,application/xhtml+xml,application/xml;q=0.9,*/*;q=0.8", "User-Agent": "Mozilla/5.0 (Windows NT 10.0; Win64; x64) AppleWebKit/537.36 (KHTML, like Gecko) Chrome/70.0.3538.31 Safari/537.36"}, "url": "https://r6---sn-25ge7nse.googlevideo.com/videoplayback?expire=1565854066&ei=ErVUXYPmBZSVkwaTzaDQDA&ip=148.163.76.139&id=o-AB-qyN0zj7U5atdxIcQvWYFcheiuJcStQgtAOw7NIjp7&itag=242&aitags=133%2C134%2C135%2C136%2C137%2C160%2C242%2C243%2C244%2C247%2C248%2C278&source=youtube&requiressl=yes&mm=31%2C29&mn=sn-25ge7nse%2Csn-25glen7e&ms=au%2Crdu&mv=u&mvi=5&pl=22&mime=video%2Fwebm&gir=yes&clen=1240285&dur=56.156&lmt=1544997310781521&mt=1565831977&fvip=6&keepalive=yes&c=WEB&txp=2301222&sparams=expire%2Cei%2Cip%2Cid%2Caitags%2Csource%2Crequiressl%2Cmime%2Cgir%2Cclen%2Cdur%2Clmt&sig=ALgxI2wwRQIhAM4gUE2jpUpFZlTwviQq9p_XTzLixh2xxbmMKRo-BhesAiBtA8EDOBVcql99UttZWaR2G6OBxF6o42hvTJbQWDZtbg%3D%3D&lsparams=mm%2Cmn%2Cms%2Cmv%2Cmvi%2Cpl&lsig=AHylml4wRQIhAJKMRBbZFB74CYBAKnuiLqB4J6TCs99X5LO2Qy7zt2UoAiBk3TbLfTK2t4HxVEBZe61QM2E7FwhJG9_1EYkDIzc3Tw%3D%3D&ratebypass=yes", "vcodec": "vp9", "player_url": "/yts/jsbin/player_ias-vflLAbfAI/en_US/base.js", "width": 426, "ext": "webm", "filesize": 1240285, "fps": 30, "acodec": "none"}, {"format_note": "240p", "protocol": "https", "format": "133 - 426x240 (240p)", "tbr": 267.38, "height": 240, "downloader_options": {"http_chunk_size": 10485760}, "format_id": "133", "quality": -1, "http_headers": {"Accept-Charset": "ISO-8859-1,utf-8;q=0.7,*;q=0.7", "Accept-Language": "en-us,en;q=0.5", "Accept-Encoding": "gzip, deflate", "Accept": "text/html,application/xhtml+xml,application/xml;q=0.9,*/*;q=0.8", "User-Agent": "Mozilla/5.0 (Windows NT 10.0; Win64; x64) AppleWebKit/537.36 (KHTML, like Gecko) Chrome/70.0.3538.31 Safari/537.36"}, "url": "https://r6---sn-25ge7nse.googlevideo.com/videoplayback?expire=1565854066&ei=ErVUXYPmBZSVkwaTzaDQDA&ip=148.163.76.139&id=o-AB-qyN0zj7U5atdxIcQvWYFcheiuJcStQgtAOw7NIjp7&itag=133&aitags=133%2C134%2C135%2C136%2C137%2C160%2C242%2C243%2C244%2C247%2C248%2C278&source=youtube&requiressl=yes&mm=31%2C29&mn=sn-25ge7nse%2Csn-25glen7e&ms=au%2Crdu&mv=u&mvi=5&pl=22&mime=video%2Fmp4&gir=yes&clen=1512885&dur=56.156&lmt=1544988176877569&mt=1565831977&fvip=6&keepalive=yes&c=WEB&txp=2311222&sparams=expire%2Cei%2Cip%2Cid%2Caitags%2Csource%2Crequiressl%2Cmime%2Cgir%2Cclen%2Cdur%2Clmt&sig=ALgxI2wwRQIgI8B0RaqI3jtOsf1p6CZRXfQf2SkdmH3JgpmCyincdogCIQCewm3KAf-EApKpYjTEq_5cYCdTmdRXYfQBlvxDt-Nuww%3D%3D&lsparams=mm%2Cmn%2Cms%2Cmv%2Cmvi%2Cpl&lsig=AHylml4wRQIhAJKMRBbZFB74CYBAKnuiLqB4J6TCs99X5LO2Qy7zt2UoAiBk3TbLfTK2t4HxVEBZe61QM2E7FwhJG9_1EYkDIzc3Tw%3D%3D&ratebypass=yes", "vcodec": "avc1.4d4015", "player_url": "/yts/jsbin/player_ias-vflLAbfAI/en_US/base.js", "width": 426, "ext": "mp4", "filesize": 1512885, "fps": 30, "acodec": "none"}, {"format_note": "360p", "protocol": "https", "format": "243 - 640x360 (360p)", "tbr": 404.654, "height": 360, "downloader_options": {"http_chunk_size": 10485760}, "format_id": "243", "quality": -1, "http_headers": {"Accept-Charset": "ISO-8859-1,utf-8;q=0.7,*;q=0.7", "Accept-Language": "en-us,en;q=0.5", "Accept-Encoding": "gzip, deflate", "Accept": "text/html,application/xhtml+xml,application/xml;q=0.9,*/*;q=0.8", "User-Agent": "Mozilla/5.0 (Windows NT 10.0; Win64; x64) AppleWebKit/537.36 (KHTML, like Gecko) Chrome/70.0.3538.31 Safari/537.36"}, "url": "https://r6---sn-25ge7nse.googlevideo.com/videoplayback?expire=1565854066&ei=ErVUXYPmBZSVkwaTzaDQDA&ip=148.163.76.139&id=o-AB-qyN0zj7U5atdxIcQvWYFcheiuJcStQgtAOw7NIjp7&itag=243&aitags=133%2C134%2C135%2C136%2C137%2C160%2C242%2C243%2C244%2C247%2C248%2C278&source=youtube&requiressl=yes&mm=31%2C29&mn=sn-25ge7nse%2Csn-25glen7e&ms=au%2Crdu&mv=u&mvi=5&pl=22&mime=video%2Fwebm&gir=yes&clen=2391241&dur=56.156&lmt=1544997311405735&mt=1565831977&fvip=6&keepalive=yes&c=WEB&txp=2301222&sparams=expire%2Cei%2Cip%2Cid%2Caitags%2Csource%2Crequiressl%2Cmime%2Cgir%2Cclen%2Cdur%2Clmt&sig=ALgxI2wwRQIhANEsUg6fNZBc6JHq6IQV4pXDEqfp1ApAx865AkUq0wMQAiAR6a5_2v7wKlm0ntHnt6SltYS8IMCMMLJ3oDvvoLXnmw%3D%3D&lsparams=mm%2Cmn%2Cms%2Cmv%2Cmvi%2Cpl&lsig=AHylml4wRQIhAJKMRBbZFB74CYBAKnuiLqB4J6TCs99X5LO2Qy7zt2UoAiBk3TbLfTK2t4HxVEBZe61QM2E7FwhJG9_1EYkDIzc3Tw%3D%3D&ratebypass=yes", "vcodec": "vp9", "player_url": "/yts/jsbin/player_ias-vflLAbfAI/en_US/base.js", "width": 640, "ext": "webm", "filesize": 2391241, "fps": 30, "acodec": "none"}, {"format_note": "360p", "protocol": "https", "format": "134 - 640x360 (360p)", "tbr": 619.179, "height": 360, "downloader_options": {"http_chunk_size": 10485760}, "format_id": "134", "quality": -1, "http_headers": {"Accept-Charset": "ISO-8859-1,utf-8;q=0.7,*;q=0.7", "Accept-Language": "en-us,en;q=0.5", "Accept-Encoding": "gzip, deflate", "Accept": "text/html,application/xhtml+xml,application/xml;q=0.9,*/*;q=0.8", "User-Agent": "Mozilla/5.0 (Windows NT 10.0; Win64; x64) AppleWebKit/537.36 (KHTML, like Gecko) Chrome/70.0.3538.31 Safari/537.36"}, "url": "https://r6---sn-25ge7nse.googlevideo.com/videoplayback?expire=1565854066&ei=ErVUXYPmBZSVkwaTzaDQDA&ip=148.163.76.139&id=o-AB-qyN0zj7U5atdxIcQvWYFcheiuJcStQgtAOw7NIjp7&itag=134&aitags=133%2C134%2C135%2C136%2C137%2C160%2C242%2C243%2C244%2C247%2C248%2C278&source=youtube&requiressl=yes&mm=31%2C29&mn=sn-25ge7nse%2Csn-25glen7e&ms=au%2Crdu&mv=u&mvi=5&pl=22&mime=video%2Fmp4&gir=yes&clen=2901063&dur=56.156&lmt=1544988176977938&mt=1565831977&fvip=6&keepalive=yes&c=WEB&txp=2311222&sparams=expire%2Cei%2Cip%2Cid%2Caitags%2Csource%2Crequiressl%2Cmime%2Cgir%2Cclen%2Cdur%2Clmt&sig=ALgxI2wwRgIhAOrb1yR2ReLn-dr1d28zswJI-rK9vI8PZS-LhPuvb5e0AiEAmmbT2Ge6g-IMFmNs5FN_iJj0zbTKHJ8Fu-cpvuWhizY%3D&lsparams=mm%2Cmn%2Cms%2Cmv%2Cmvi%2Cpl&lsig=AHylml4wRQIhAJKMRBbZFB74CYBAKnuiLqB4J6TCs99X5LO2Qy7zt2UoAiBk3TbLfTK2t4HxVEBZe61QM2E7FwhJG9_1EYkDIzc3Tw%3D%3D&ratebypass=yes", "vcodec": "avc1.4d401e", "player_url": "/yts/jsbin/player_ias-vflLAbfAI/en_US/base.js", "width": 640, "ext": "mp4", "filesize": 2901063, "fps": 30, "acodec": "none"}, {"format_note": "480p", "protocol": "https", "format": "244 - 854x480 (480p)", "tbr": 751.52, "height": 480, "downloader_options": {"http_chunk_size": 10485760}, "format_id": "244", "quality": -1, "http_headers": {"Accept-Charset": "ISO-8859-1,utf-8;q=0.7,*;q=0.7", "Accept-Language": "en-us,en;q=0.5", "Accept-Encoding": "gzip, deflate", "Accept": "text/html,application/xhtml+xml,application/xml;q=0.9,*/*;q=0.8", "User-Agent": "Mozilla/5.0 (Windows NT 10.0; Win64; x64) AppleWebKit/537.36 (KHTML, like Gecko) Chrome/70.0.3538.31 Safari/537.36"}, "url": "https://r6---sn-25ge7nse.googlevideo.com/videoplayback?expire=1565854066&ei=ErVUXYPmBZSVkwaTzaDQDA&ip=148.163.76.139&id=o-AB-qyN0zj7U5atdxIcQvWYFcheiuJcStQgtAOw7NIjp7&itag=244&aitags=133%2C134%2C135%2C136%2C137%2C160%2C242%2C243%2C244%2C247%2C248%2C278&source=youtube&requiressl=yes&mm=31%2C29&mn=sn-25ge7nse%2Csn-25glen7e&ms=au%2Crdu&mv=u&mvi=5&pl=22&mime=video%2Fwebm&gir=yes&clen=4441448&dur=56.156&lmt=1544997310786022&mt=1565831977&fvip=6&keepalive=yes&c=WEB&txp=2301222&sparams=expire%2Cei%2Cip%2Cid%2Caitags%2Csource%2Crequiressl%2Cmime%2Cgir%2Cclen%2Cdur%2Clmt&sig=ALgxI2wwRgIhAIAYs5DuZN8jc6UR_X20Xr7VF3w1eWwtRCXL9PPC_T_YAiEA2QxpWx_mTsZF6QGMlVw9j3jwfRGhFpGmT0trb3lq_fw%3D&lsparams=mm%2Cmn%2Cms%2Cmv%2Cmvi%2Cpl&lsig=AHylml4wRQIhAJKMRBbZFB74CYBAKnuiLqB4J6TCs99X5LO2Qy7zt2UoAiBk3TbLfTK2t4HxVEBZe61QM2E7FwhJG9_1EYkDIzc3Tw%3D%3D&ratebypass=yes", "vcodec": "vp9", "player_url": "/yts/jsbin/player_ias-vflLAbfAI/en_US/base.js", "width": 854, "ext": "webm", "filesize": 4441448, "fps": 30, "acodec": "none"}, {"format_note": "480p", "protocol": "https", "format": "135 - 854x480 (480p)", "tbr": 1095.117, "height": 480, "downloader_options": {"http_chunk_size": 10485760}, "format_id": "135", "quality": -1, "http_headers": {"Accept-Charset": "ISO-8859-1,utf-8;q=0.7,*;q=0.7", "Accept-Language": "en-us,en;q=0.5", "Accept-Encoding": "gzip, deflate", "Accept": "text/html,application/xhtml+xml,application/xml;q=0.9,*/*;q=0.8", "User-Agent": "Mozilla/5.0 (Windows NT 10.0; Win64; x64) AppleWebKit/537.36 (KHTML, like Gecko) Chrome/70.0.3538.31 Safari/537.36"}, "url": "https://r6---sn-25ge7nse.googlevideo.com/videoplayback?expire=1565854066&ei=ErVUXYPmBZSVkwaTzaDQDA&ip=148.163.76.139&id=o-AB-qyN0zj7U5atdxIcQvWYFcheiuJcStQgtAOw7NIjp7&itag=135&aitags=133%2C134%2C135%2C136%2C137%2C160%2C242%2C243%2C244%2C247%2C248%2C278&source=youtube&requiressl=yes&mm=31%2C29&mn=sn-25ge7nse%2Csn-25glen7e&ms=au%2Crdu&mv=u&mvi=5&pl=22&mime=video%2Fmp4&gir=yes&clen=5352035&dur=56.156&lmt=1544988177072004&mt=1565831977&fvip=6&keepalive=yes&c=WEB&txp=2311222&sparams=expire%2Cei%2Cip%2Cid%2Caitags%2Csource%2Crequiressl%2Cmime%2Cgir%2Cclen%2Cdur%2Clmt&sig=ALgxI2wwRQIgWf4a_-Fm8tDboGqAyq6tuRfYGSHRohKTiSF6OYsezokCIQD0DJtzPidyyaF8NYOP6CW_KVyEB2is5nRznSOxZsiJag%3D%3D&lsparams=mm%2Cmn%2Cms%2Cmv%2Cmvi%2Cpl&lsig=AHylml4wRQIhAJKMRBbZFB74CYBAKnuiLqB4J6TCs99X5LO2Qy7zt2UoAiBk3TbLfTK2t4HxVEBZe61QM2E7FwhJG9_1EYkDIzc3Tw%3D%3D&ratebypass=yes", "vcodec": "avc1.4d401f", "player_url": "/yts/jsbin/player_ias-vflLAbfAI/en_US/base.js", "width": 854, "ext": "mp4", "filesize": 5352035, "fps": 30, "acodec": "none"}, {"format_note": "720p", "protocol": "https", "format": "247 - 1280x720 (720p)", "tbr": 1505.441, "height": 720, "downloader_options": {"http_chunk_size": 10485760}, "format_id": "247", "quality": -1, "http_headers": {"Accept-Charset": "ISO-8859-1,utf-8;q=0.7,*;q=0.7", "Accept-Language": "en-us,en;q=0.5", "Accept-Encoding": "gzip, deflate", "Accept": "text/html,application/xhtml+xml,application/xml;q=0.9,*/*;q=0.8", "User-Agent": "Mozilla/5.0 (Windows NT 10.0; Win64; x64) AppleWebKit/537.36 (KHTML, like Gecko) Chrome/70.0.3538.31 Safari/537.36"}, "url": "https://r6---sn-25ge7nse.googlevideo.com/videoplayback?expire=1565854066&ei=ErVUXYPmBZSVkwaTzaDQDA&ip=148.163.76.139&id=o-AB-qyN0zj7U5atdxIcQvWYFcheiuJcStQgtAOw7NIjp7&itag=247&aitags=133%2C134%2C135%2C136%2C137%2C160%2C242%2C243%2C244%2C247%2C248%2C278&source=youtube&requiressl=yes&mm=31%2C29&mn=sn-25ge7nse%2Csn-25glen7e&ms=au%2Crdu&mv=u&mvi=5&pl=22&mime=video%2Fwebm&gir=yes&clen=9779003&dur=56.156&lmt=1544997310787456&mt=1565831977&fvip=6&keepalive=yes&c=WEB&txp=2301222&sparams=expire%2Cei%2Cip%2Cid%2Caitags%2Csource%2Crequiressl%2Cmime%2Cgir%2Cclen%2Cdur%2Clmt&sig=ALgxI2wwRQIgdGx31SFFh503PEUa0WNyZkI6s0iWMsAv5FyjFdJqIs8CIQCpyHugbIHZkGg8R06AoT2sfexXshdzwqXC81gcouZV3g%3D%3D&lsparams=mm%2Cmn%2Cms%2Cmv%2Cmvi%2Cpl&lsig=AHylml4wRQIhAJKMRBbZFB74CYBAKnuiLqB4J6TCs99X5LO2Qy7zt2UoAiBk3TbLfTK2t4HxVEBZe61QM2E7FwhJG9_1EYkDIzc3Tw%3D%3D&ratebypass=yes", "vcodec": "vp9", "player_url": "/yts/jsbin/player_ias-vflLAbfAI/en_US/base.js", "width": 1280, "ext": "webm", "filesize": 9779003, "fps": 30, "acodec": "none"}, {"format_note": "720p", "protocol": "https", "format": "136 - 1280x720 (720p)", "tbr": 2258.232, "height": 720, "downloader_options": {"http_chunk_size": 10485760}, "format_id": "136", "quality": -1, "http_headers": {"Accept-Charset": "ISO-8859-1,utf-8;q=0.7,*;q=0.7", "Accept-Language": "en-us,en;q=0.5", "Accept-Encoding": "gzip, deflate", "Accept": "text/html,application/xhtml+xml,application/xml;q=0.9,*/*;q=0.8", "User-Agent": "Mozilla/5.0 (Windows NT 10.0; Win64; x64) AppleWebKit/537.36 (KHTML, like Gecko) Chrome/70.0.3538.31 Safari/537.36"}, "url": "https://r6---sn-25ge7nse.googlevideo.com/videoplayback?expire=1565854066&ei=ErVUXYPmBZSVkwaTzaDQDA&ip=148.163.76.139&id=o-AB-qyN0zj7U5atdxIcQvWYFcheiuJcStQgtAOw7NIjp7&itag=136&aitags=133%2C134%2C135%2C136%2C137%2C160%2C242%2C243%2C244%2C247%2C248%2C278&source=youtube&requiressl=yes&mm=31%2C29&mn=sn-25ge7nse%2Csn-25glen7e&ms=au%2Crdu&mv=u&mvi=5&pl=22&mime=video%2Fmp4&gir=yes&clen=11043614&dur=56.156&lmt=1544988177177676&mt=1565831977&fvip=6&keepalive=yes&c=WEB&txp=2311222&sparams=expire%2Cei%2Cip%2Cid%2Caitags%2Csource%2Crequiressl%2Cmime%2Cgir%2Cclen%2Cdur%2Clmt&sig=ALgxI2wwRQIgQzBSSJnlQgo9o4UeTtVdv-y2CPQvUjL3cSbt9nkpOqcCIQCezwVOH8Pd1sZpkJz5fu6GLzu-u2cEsS5EUhhAD1BDdw%3D%3D&lsparams=mm%2Cmn%2Cms%2Cmv%2Cmvi%2Cpl&lsig=AHylml4wRQIhAJKMRBbZFB74CYBAKnuiLqB4J6TCs99X5LO2Qy7zt2UoAiBk3TbLfTK2t4HxVEBZe61QM2E7FwhJG9_1EYkDIzc3Tw%3D%3D&ratebypass=yes", "vcodec": "avc1.4d401f", "player_url": "/yts/jsbin/player_ias-vflLAbfAI/en_US/base.js", "width": 1280, "ext": "mp4", "filesize": 11043614, "fps": 30, "acodec": "none"}, {"format_note": "1080p", "protocol": "https", "format": "248 - 1920x1080 (1080p)", "tbr": 2639.89, "height": 1080, "downloader_options": {"http_chunk_size": 10485760}, "format_id": "248", "quality": -1, "http_headers": {"Accept-Charset": "ISO-8859-1,utf-8;q=0.7,*;q=0.7", "Accept-Language": "en-us,en;q=0.5", "Accept-Encoding": "gzip, deflate", "Accept": "text/html,application/xhtml+xml,application/xml;q=0.9,*/*;q=0.8", "User-Agent": "Mozilla/5.0 (Windows NT 10.0; Win64; x64) AppleWebKit/537.36 (KHTML, like Gecko) Chrome/70.0.3538.31 Safari/537.36"}, "url": "https://r6---sn-25ge7nse.googlevideo.com/videoplayback?expire=1565854066&ei=ErVUXYPmBZSVkwaTzaDQDA&ip=148.163.76.139&id=o-AB-qyN0zj7U5atdxIcQvWYFcheiuJcStQgtAOw7NIjp7&itag=248&aitags=133%2C134%2C135%2C136%2C137%2C160%2C242%2C243%2C244%2C247%2C248%2C278&source=youtube&requiressl=yes&mm=31%2C29&mn=sn-25ge7nse%2Csn-25glen7e&ms=au%2Crdu&mv=u&mvi=5&pl=22&mime=video%2Fwebm&gir=yes&clen=17875590&dur=56.156&lmt=1544997310780155&mt=1565831977&fvip=6&keepalive=yes&c=WEB&txp=2301222&sparams=expire%2Cei%2Cip%2Cid%2Caitags%2Csource%2Crequiressl%2Cmime%2Cgir%2Cclen%2Cdur%2Clmt&sig=ALgxI2wwRQIhAIAmtMTc3Grqjr9Yz4E32HRnw5m17gMLOU2MngNDo0iAAiBBtTo2vlWydXxTf9XRp1JwIkogSUCs7xMKmcu8EmcdUw%3D%3D&lsparams=mm%2Cmn%2Cms%2Cmv%2Cmvi%2Cpl&lsig=AHylml4wRQIhAJKMRBbZFB74CYBAKnuiLqB4J6TCs99X5LO2Qy7zt2UoAiBk3TbLfTK2t4HxVEBZe61QM2E7FwhJG9_1EYkDIzc3Tw%3D%3D&ratebypass=yes", "vcodec": "vp9", "player_url": "/yts/jsbin/player_ias-vflLAbfAI/en_US/base.js", "width": 1920, "ext": "webm", "filesize": 17875590, "fps": 30, "acodec": "none"}, {"format_note": "1080p", "protocol": "https", "format": "137 - 1920x1080 (1080p)", "tbr": 4426.33, "height": 1080, "downloader_options": {"http_chunk_size": 10485760}, "format_id": "137", "quality": -1, "http_headers": {"Accept-Charset": "ISO-8859-1,utf-8;q=0.7,*;q=0.7", "Accept-Language": "en-us,en;q=0.5", "Accept-Encoding": "gzip, deflate", "Accept": "text/html,application/xhtml+xml,application/xml;q=0.9,*/*;q=0.8", "User-Agent": "Mozilla/5.0 (Windows NT 10.0; Win64; x64) AppleWebKit/537.36 (KHTML, like Gecko) Chrome/70.0.3538.31 Safari/537.36"}, "url": "https://r6---sn-25ge7nse.googlevideo.com/videoplayback?expire=1565854066&ei=ErVUXYPmBZSVkwaTzaDQDA&ip=148.163.76.139&id=o-AB-qyN0zj7U5atdxIcQvWYFcheiuJcStQgtAOw7NIjp7&itag=137&aitags=133%2C134%2C135%2C136%2C137%2C160%2C242%2C243%2C244%2C247%2C248%2C278&source=youtube&requiressl=yes&mm=31%2C29&mn=sn-25ge7nse%2Csn-25glen7e&ms=au%2Crdu&mv=u&mvi=5&pl=22&mime=video%2Fmp4&gir=yes&clen=22763021&dur=56.156&lmt=1544988177371167&mt=1565831977&fvip=6&keepalive=yes&c=WEB&txp=2311222&sparams=expire%2Cei%2Cip%2Cid%2Caitags%2Csource%2Crequiressl%2Cmime%2Cgir%2Cclen%2Cdur%2Clmt&sig=ALgxI2wwRQIgQx9TQogieG3CJpVdXop7POlC6v42jUQwakMhAYdNDJQCIQC6ywp1Zn7dsfKJQ_QvBmUuj53ZDzTm2GmsbdBkWqi8Bw%3D%3D&lsparams=mm%2Cmn%2Cms%2Cmv%2Cmvi%2Cpl&lsig=AHylml4wRQIhAJKMRBbZFB74CYBAKnuiLqB4J6TCs99X5LO2Qy7zt2UoAiBk3TbLfTK2t4HxVEBZe61QM2E7FwhJG9_1EYkDIzc3Tw%3D%3D&ratebypass=yes", "vcodec": "avc1.640028", "player_url": "/yts/jsbin/player_ias-vflLAbfAI/en_US/base.js", "width": 1920, "ext": "mp4", "filesize": 22763021, "fps": 30, "acodec": "none"}, {"asr": null, "format_note": "medium", "protocol": "https", "http_headers": {"Accept-Charset": "ISO-8859-1,utf-8;q=0.7,*;q=0.7", "Accept-Language": "en-us,en;q=0.5", "Accept-Encoding": "gzip, deflate", "Accept": "text/html,application/xhtml+xml,application/xml;q=0.9,*/*;q=0.8", "User-Agent": "Mozilla/5.0 (Windows NT 10.0; Win64; x64) AppleWebKit/537.36 (KHTML, like Gecko) Chrome/70.0.3538.31 Safari/537.36"}, "format": "43 - 640x360 (medium)", "url": "https://r6---sn-25ge7nse.googlevideo.com/videoplayback?expire=1565854066&ei=ErVUXYPmBZSVkwaTzaDQDA&ip=148.163.76.139&id=o-AB-qyN0zj7U5atdxIcQvWYFcheiuJcStQgtAOw7NIjp7&itag=43&source=youtube&requiressl=yes&mm=31%2C29&mn=sn-25ge7nse%2Csn-25glen7e&ms=au%2Crdu&mv=u&mvi=5&pl=22&mime=video%2Fwebm&gir=yes&clen=6055653&ratebypass=yes&dur=0.000&lmt=1544995238223775&mt=1565831977&fvip=6&c=WEB&txp=2301222&sparams=expire%2Cei%2Cip%2Cid%2Citag%2Csource%2Crequiressl%2Cmime%2Cgir%2Cclen%2Cratebypass%2Cdur%2Clmt&sig=ALgxI2wwRgIhAK2F-vMgVdYdyTohHGkFivG07uloRCYR2wDIjM1-abYuAiEA7zZ1AYhAcvpnV0z3BLNreevS8SMPhmDhgxuKWXz2X4M%3D&lsparams=mm%2Cmn%2Cms%2Cmv%2Cmvi%2Cpl&lsig=AHylml4wRQIhAJKMRBbZFB74CYBAKnuiLqB4J6TCs99X5LO2Qy7zt2UoAiBk3TbLfTK2t4HxVEBZe61QM2E7FwhJG9_1EYkDIzc3Tw%3D%3D", "vcodec": "vp8.0", "tbr": null, "ext": "webm", "player_url": "/yts/jsbin/player_ias-vflLAbfAI/en_US/base.js", "width": 640, "abr": 128, "filesize": 6055653, "fps": null, "format_id": "43", "height": 360, "quality": 1, "acodec": "vorbis"}, {"asr": 44100, "format_note": "medium", "protocol": "https", "http_headers": {"Accept-Charset": "ISO-8859-1,utf-8;q=0.7,*;q=0.7", "Accept-Language": "en-us,en;q=0.5", "Accept-Encoding": "gzip, deflate", "Accept": "text/html,application/xhtml+xml,application/xml;q=0.9,*/*;q=0.8", "User-Agent": "Mozilla/5.0 (Windows NT 10.0; Win64; x64) AppleWebKit/537.36 (KHTML, like Gecko) Chrome/70.0.3538.31 Safari/537.36"}, "format": "18 - 640x360 (medium)", "url": "https://r6---sn-25ge7nse.googlevideo.com/videoplayback?expire=1565854066&ei=ErVUXYPmBZSVkwaTzaDQDA&ip=148.163.76.139&id=o-AB-qyN0zj7U5atdxIcQvWYFcheiuJcStQgtAOw7NIjp7&itag=18&source=youtube&requiressl=yes&mm=31%2C29&mn=sn-25ge7nse%2Csn-25glen7e&ms=au%2Crdu&mv=u&mvi=5&pl=22&mime=video%2Fmp4&gir=yes&clen=3290076&ratebypass=yes&dur=56.215&lmt=1544988045288806&mt=1565831977&fvip=6&c=WEB&txp=2301222&sparams=expire%2Cei%2Cip%2Cid%2Citag%2Csource%2Crequiressl%2Cmime%2Cgir%2Cclen%2Cratebypass%2Cdur%2Clmt&sig=ALgxI2wwRQIgT4Bzwe9Cri2fU06uXsW5tX2A4lRk8QpaRMPuXl_xFHYCIQCezcdI3kdldXJeoMxnt6LdptFSldpo-8zJDV_iqTtLlQ%3D%3D&lsparams=mm%2Cmn%2Cms%2Cmv%2Cmvi%2Cpl&lsig=AHylml4wRQIhAJKMRBbZFB74CYBAKnuiLqB4J6TCs99X5LO2Qy7zt2UoAiBk3TbLfTK2t4HxVEBZe61QM2E7FwhJG9_1EYkDIzc3Tw%3D%3D", "vcodec": "avc1.42001E", "tbr": 468.213, "ext": "mp4", "player_url": "/yts/jsbin/player_ias-vflLAbfAI/en_US/base.js", "width": 640, "abr": 96, "filesize": 3290076, "fps": null, "format_id": "18", "height": 360, "quality": 1, "acodec": "mp4a.40.2"}, {"asr": 44100, "format_note": "hd720", "protocol": "https", "http_headers": {"Accept-Charset": "ISO-8859-1,utf-8;q=0.7,*;q=0.7", "Accept-Language": "en-us,en;q=0.5", "Accept-Encoding": "gzip, deflate", "Accept": "text/html,application/xhtml+xml,application/xml;q=0.9,*/*;q=0.8", "User-Agent": "Mozilla/5.0 (Windows NT 10.0; Win64; x64) AppleWebKit/537.36 (KHTML, like Gecko) Chrome/70.0.3538.31 Safari/537.36"}, "format": "22 - 1280x720 (hd720)", "url": "https://r6---sn-25ge7nse.googlevideo.com/videoplayback?expire=1565854066&ei=ErVUXYPmBZSVkwaTzaDQDA&ip=148.163.76.139&id=o-AB-qyN0zj7U5atdxIcQvWYFcheiuJcStQgtAOw7NIjp7&itag=22&source=youtube&requiressl=yes&mm=31%2C29&mn=sn-25ge7nse%2Csn-25glen7e&ms=au%2Crdu&mv=u&mvi=5&pl=22&mime=video%2Fmp4&ratebypass=yes&dur=56.238&lmt=1544988206023116&mt=1565831977&fvip=6&c=WEB&txp=2311222&sparams=expire%2Cei%2Cip%2Cid%2Citag%2Csource%2Crequiressl%2Cmime%2Cratebypass%2Cdur%2Clmt&sig=ALgxI2wwRQIhAKFWpr6xf4MXd4zyD-ebvHA4bxWW5c99CGahNKHEPjk9AiBXCLWwYI_dTVdryhMEnIS0x4CC2Tgfzq4tviwAQd4ihQ%3D%3D&lsparams=mm%2Cmn%2Cms%2Cmv%2Cmvi%2Cpl&lsig=AHylml4wRQIhAJKMRBbZFB74CYBAKnuiLqB4J6TCs99X5LO2Qy7zt2UoAiBk3TbLfTK2t4HxVEBZe61QM2E7FwhJG9_1EYkDIzc3Tw%3D%3D", "vcodec": "avc1.64001F", "tbr": 1702.268, "ext": "mp4", "player_url": "/yts/jsbin/player_ias-vflLAbfAI/en_US/base.js", "width": 1280, "abr": 192, "filesize": null, "fps": null, "format_id": "22", "height": 720, "quality": 2, "acodec": "mp4a.40.2"}], "playlist_uploader_id": "UC2VwgzDzUNvfRDqQ6LJxTXA", "channel_url": "http://www.youtube.com/channel/UC2VwgzDzUNvfRDqQ6LJxTXA", "resolution": null, "width": 1920, "n_entries": 488, "age_limit": 0}